{"cameraMode":{"drawMode":0,"name":"Shaded","section":"Shading Mode"},"sceneLighting":true,"audioPlay":false,"sceneViewState":{"m_AlwaysRefresh":false,"showFog":true,"showSkybox":true,"showFlares":true,"showImageEffects":true,"showParticleSystems":true,"showVisualEffectGraphs":true,"m_FxEnabled":true},"in2DMode":false,"pivot":{"x":319.9776916503906,"y":408.50738525390627,"z":-103.08683013916016},"rotation":{"x":-0.042190197855234149,"y":0.07097386568784714,"z":-0.003004872240126133,"w":-0.9965826869010925},"size":10.0,"orthographic":false}